ISR/__init__.py
ISR/assistant.py
ISR/models/__init__.py
ISR/models/cut_vgg19.py
ISR/models/discriminator.py
ISR/models/imagemodel.py
ISR/models/rdn.py
ISR/models/rrdn.py
ISR/predict/__init__.py
ISR/predict/predictor.py
ISR/train/__init__.py
ISR/train/trainer.py
ISR/utils/__init__.py
ISR/utils/datahandler.py
ISR/utils/image_processing.py
ISR/utils/logger.py
ISR/utils/metrics.py
ISR/utils/train_helper.py
ISR/utils/utils.py
ISR-2.2.0.dist-info/LICENSE
ISR-2.2.0.dist-info/METADATA
ISR-2.2.0.dist-info/WHEEL
ISR-2.2.0.dist-info/top_level.txt
ISR-2.2.0.dist-info/RECORD
